Workbook
Name taxa_mensal: Simulador!$D$12
Name prazo_anos: Simulador!$D$11
Name aporte: Simulador!$D$10

Sheet Simulador
C3: SIMULADOR DE INVESTIMENTOS EM FIIs
C5: Preencha os campos brancos (editáveis). As células verdes são calculadas automaticamente.
C7: 1. PARÂMETROS DA SIMULAÇÃO | G7: 3. PROJEÇÃO DE CENÁRIOS DE TEMPO
C8: Salário Mensal (R$): | D8: 5000 | G8: Anos | H8: Patrimônio Acumulado | I8: Dividendos/Mês
C9: Sugestão de Aporte (30%): | D9: =D8*0.3 -> 1500 | G9: 2 | H9: =FV(taxa_mensal, G9*12, -aporte, 0, 0) -> 39514.733 | I9: =H9*taxa_mensal -> 316.11786
C10: Quanto Investir por Mês (Aporte): | D10: 1500 | G10: 5 | H10: =FV(taxa_mensal, G10*12, -aporte, 0, 0) -> 114935.8 | I10: =H10*taxa_mensal -> 919.4864
C11: Por Quantos Anos (Prazo): | D11: 10 | G11: 10 | H11: =FV(taxa_mensal, G11*12, -aporte, 0, 0) -> 300326.2 | I11: =H11*taxa_mensal -> 2402.6096
C12: Taxa de Rendimento Mensal (%): | D12: 0.008 | G12: 20 | H12: =FV(taxa_mensal, G12*12, -aporte, 0, 0) -> 1081696.8 | I12: =H12*taxa_mensal -> 8653.5746
G13: 30 | H13: =FV(taxa_mensal, G13*12, -aporte, 0, 0) -> 3114619.8 | I13: =H13*taxa_mensal -> 24916.959
C14: 2. RESULTADOS PRINCIPAIS
C15: Patrimônio Acumulado: | D15: =FV(taxa_mensal, prazo_anos*12, -aporte, 0, 0) -> 300326.2
C16: Dividendos Mensais Estimados: | D16: =D15*taxa_mensal -> 2402.6096
C18: 4. DIVISÃO DA CARTEIRA POR PERFIL DE INVESTIDOR
C19: Selecione o Perfil de Investidor: | E19: Moderado
C21: Tipo de Fundo (FII) | D21: % Alocado | E21: Aporte Mensal (R$)
C22: Tijolo | D22: =VLOOKUP($E$19&C22, Apoio!A:D, 4, FALSE) -> 0.4 | E22: =aporte*D22 -> 600
C23: Papel | D23: =VLOOKUP($E$19&C23, Apoio!A:D, 4, FALSE) -> 0.35 | E23: =aporte*D23 -> 525
C24: FOF | D24: =VLOOKUP($E$19&C24, Apoio!A:D, 4, FALSE) -> 0.15 | E24: =aporte*D24 -> 225
C25: Desenvolvimento | D25: =VLOOKUP($E$19&C25, Apoio!A:D, 4, FALSE) -> 0.05 | E25: =aporte*D25 -> 75
C26: Infraestrutura | D26: =VLOOKUP($E$19&C26,Apoio!A:D,4,FALSE) -> 0.05 | E26: =aporte*D26 -> 75
C27: Outros | D27: =VLOOKUP($E$19&C27, Apoio!A:D, 4, FALSE) -> 0 | E27: =aporte*D27 -> 0
C28: Total | D28: =SUM(D22:D27) -> 1 | E28: =SUM(E22:E27) -> 1500

Sheet Apoio
A1: Chave Composta | B1: Perfil | C1: Tipo FII | D1: Percentual (%)
A2: ConservadorTijolo | B2: Conservador | C2: Tijolo | D2: 0.5
A3: ConservadorPapel | B3: Conservador | C3: Papel | D3: 0.3
A4: ConservadorFOF | B4: Conservador | C4: FOF | D4: 0.2
A5: ConservadorDesenvolvimento | B5: Conservador | C5: Desenvolvimento | D5: 0
A6: ConservadorInfraestrutura | B6: Conservador | C6: Infraestrutura | D6: 0
A7: ConservadorOutros | B7: Conservador | C7: Outros | D7: 0
A8: ModeradoTijolo | B8: Moderado | C8: Tijolo | D8: 0.4
A9: ModeradoPapel | B9: Moderado | C9: Papel | D9: 0.35
A10: ModeradoFOF | B10: Moderado | C10: FOF | D10: 0.15
A11: ModeradoDesenvolvimento | B11: Moderado | C11: Desenvolvimento | D11: 0.05
A12: ModeradoInfraestrutura | B12: Moderado | C12: Infraestrutura | D12: 0.05
A13: ModeradoOutros | B13: Moderado | C13: Outros | D13: 0
... A19: ArrojadoOutros | B19: Arrojado | C19: Outros | D19: 0.05
